rpgt/__init__.py
rpgt/src/__init__.py
rpgt/src/__main__.py
rpgt/src/cli/__init__.py
rpgt/src/cli/cli.py
rpgt/src/factories/__init__.py
rpgt/src/factories/env_factory.py
rpgt/src/factories/field_factory.py
rpgt/src/factories/vcp_factory.py
rpgt/src/generators/__init__.py
rpgt/src/generators/changelog_generator.py
rpgt/src/generators/contributing_generator.py
rpgt/src/generators/dockerfile_generator.py
rpgt/src/generators/dvc_generator.py
rpgt/src/generators/generator.py
rpgt/src/generators/githooks_generator.py
rpgt/src/generators/licence_generator.py
rpgt/src/generators/readme_generator.py
rpgt/src/generators/setup_py_generator.py
rpgt/src/generators/structure_generator.py
rpgt/src/generators/cicd/__init__.py
rpgt/src/generators/cicd/cicd_generator.py
rpgt/src/generators/cicd/github_ci_generator.py
rpgt/src/generators/cicd/gitlab_ci_generator.py
rpgt/src/generators/environment/__init__.py
rpgt/src/generators/environment/environment_generator.py
rpgt/src/generators/environment/pipenv_generator.py
rpgt/src/setup/__init__.py
rpgt/src/setup/mllint_setup.py
rpgt/src/setup/package_setup.py
rpgt/src/setup/pytest_setup.py
rpgt/src/setup/setup.py
rpgt/src/setup/environment/__init__.py
rpgt/src/setup/environment/environment_setup.py
rpgt/src/setup/environment/pipenv_setup.py
rpgt/src/setup/field/__init__.py
rpgt/src/setup/field/dl_setup.py
rpgt/src/setup/field/field_setup.py
rpgt/src/setup/field/ml_setup.py
rpgt/src/setup/field/rl_setup.py
rpgt/src/setup/vcp/__init__.py
rpgt/src/setup/vcp/github_setup.py
rpgt/src/setup/vcp/gitlab_setup.py
rpgt/src/setup/vcp/vcp_setup.py
rpgt/src/utils/__init__.py
rpgt/src/utils/file_reader.py
rpgt/src/utils/file_system.py
rpgt/templates/__init__.py
rpgt/templates/code/__init__.py
rpgt/templates/code/__main__.py
rpgt/templates/code/math_utils.py
rpgt/templates/code/pytorch/__init__.py
rpgt/templates/code/pytorch/get_data.txt
rpgt/templates/code/pytorch/model.txt
rpgt/templates/code/pytorch/train.txt
rpgt/templates/code/pytorch/validate.txt
rpgt-1.0.0.dist-info/LICENSE.md
rpgt-1.0.0.dist-info/METADATA
rpgt-1.0.0.dist-info/WHEEL
rpgt-1.0.0.dist-info/entry_points.txt
rpgt-1.0.0.dist-info/top_level.txt
rpgt-1.0.0.dist-info/RECORD
