Metadata-Version: 2.1
Name: rpgt
Version: 1.0.0
Summary: Automated Repository and Pipeline Generation for Data-Science Projects.
Home-page: https://gitlab.com/tweet.dimitri/rpgt
License: MIT
Platform: UNKNOWN
Requires-Python: >=3.6
Requires-Dist: pipenv
Requires-Dist: mllint
Requires-Dist: isort
Requires-Dist: pylint
Requires-Dist: mypy
Requires-Dist: bandit
Requires-Dist: black
Requires-Dist: dvc
